README.rst
setup.cfg
setup.py
maestro/__init__.py
pymaestro.egg-info/PKG-INFO
pymaestro.egg-info/SOURCES.txt
pymaestro.egg-info/dependency_links.txt
pymaestro.egg-info/requires.txt
pymaestro.egg-info/top_level.txt